{
  "0": {
   "name": "البنفسج الإفريقي (سانتباوليا إيونانثا)",
    "description": "نبات داخلي مزهر بأزهار صغيرة متعددة الألوان وأوراق ناعمة.",
    "light": "يفضل الضوء غير المباشر المتوسط.",
    "temperature": "بين 18-24 ",
    "watering": "6",
    "soil": "تربة خفيفة جيدة التصريف.",
    "fertilization": "مرة كل أسبوعين في الربيع والصيف.",
    "benefits": "يضفي لمسة جمالية بأزهاره الملونة.",
    "warning": "غير سام للحيوانات الأليفة."
  },
  "1": {
    "name": "صبار الشعر (الألوفيرا) ",
    "description": "نبات عصاري بأوراق سميكة تحتوي على جل مفيد.",
    "light": "يفضل الضوء الساطع المباشر.",
    "temperature": "بين 20-30 ",
    "watering" :"2",
   "soil": "تربة رملية جيدة التصريف.",
    "fertilization": "مرة كل شهر في الربيع والصيف.",
    "benefits": "يستخدم جل الأوراق في العلاجات الطبيعية.",
    "warning": "قد يكون سامًا للحيوانات الأليفة عند الابتلاع."
  },
  "2": {
   "name": "أنثوريوم",
   "description": "نبات داخلي مزهر بأزهار حمراء لامعة وأوراق خضراء داكنة.",
    "light": "يفضل الضوء غير المباشر الساطع.",
    "temperature": "بين 20-25 ",
    "watering": "6",
   "soil": "تربة خفيفة جيدة التصريف.",
    "fertilization": "مرة كل شهر في الربيع والصيف.",
    "benefits": "يضفي لمسة جمالية بأزهاره المميزة.",
    "warning": "سام للحيوانات الأليفة عند الابتلاع."
  },
  "3": {
   "name": "نخيل الأريكا (ديسبسيز لوتيسينس)",
  "description": "نبات داخلي بأوراق ريشية طويلة تضفي مظهرًا استوائيًا.",
  "light": "يفضل الضوء غير المباشر الساطع.",
     "temperature": "بين 18-24 ",
   "watering": "8",
  "soil": "تربة خفيفة جيدة التصريف.",
    "fertilization": "مرة كل شهر في الربيع والصيف.",
   "benefits": "ينقي الهواء ويضفي جمالًا للمساحات الداخلية.",
   "warning": "غير سام للحيوانات الأليفة."
  },
  "4": {
   "name": "سرخس الهيلون (سبرينجيري)",
   "description": "نبات داخلي بأوراق ريشية ناعمة تشبه الهليون.",
   "light": "يفضل الضوء غير المباشر المتوسط.",
    "temperature": "بين 18-24 ",
    "watering": "8",
    "soil": "تربة خفيفة جيدة التصريف.",
   "fertilization": "مرة كل شهر في الربيع والصيف.",
   "benefits": "يضفي لمسة خضراء ناعمة للمساحات الداخلية.",
   "warning": "قد يكون سامًا للحيوانات الأليفة عند الابتلاع."
  },
  "5": {
   "name": "بيجونيا",
   "description": "نبات مزهر داخلي بأزهار ملونة وأوراق جذابة.",
    "light": "يفضل الضوء غير المباشر الساطع.",
    "temperature": "بين 18-24 ",
    "watering": "8",
    "soil": "تربة خفيفة جيدة التصريف.",
    "fertilization": "مرة كل أسبوعين في الربيع والصيف.",
    "benefits": "يضفي ألوانًا زاهية للمساحات الداخلية.",
   "warning": "قد يكون سامًا للحيوانات الأليفة عند الابتلاع."
  },
  "6": {
    "name": "طائر الجنة( ستريلوتزيا ريجينيا) ",
    "description": "نبات داخلي كبير بأوراق طويلة وزهور تشبه الطيور.",
    "light": "يفضل الضوء الساطع المباشر.",
    "temperature": "بين 20-30 ",
    "watering": "4",
    "soil": "تربة خفيفة جيدة التصريف.",
    "fertilization": "مرة كل شهر في الربيع والصيف.",
    "benefits": "يضفي مظهرًا استوائيًا وزهورًا فريدة.",
    "warning": "غير سام للحيوانات الأليفة."
  },
  "7": {
    "name": "سرخس عش الطائر ( أسبلينيوم نيدوس) ",
    "description": "نبات داخلي بأوراق خضراء لامعة تنمو بشكل دائري.",
    "light": "يفضل الضوء غير المباشر الساطع.",
    "temperature": "بين 18-24 ",
    "watering": "6",
    "soil": "تربة خفيفة جيدة التصريف.",
    "fertilization": "مرة كل شهر في الربيع والصيف.",
    "benefits": "يضفي لمسة خضراء وجمالية للمساحات الداخلية.",
   "warning": "غير سام للحيوانات الأليفة."
  },
  "8": {
    "name": "سرخس بوسطن ( نيفروليبس إكزالاتا)",
    "description": "نبات داخلي بأوراق ريشية متدلية تضفي مظهرًا ناعمًا.",
   "light": "يفضل الضوء غير المباشر المتوسط.",
    "temperature": "بين 15-24 ",
    "watering": "10",
   "soil": "تربة خفيفة جيدة التصريف.",
   "fertilization": "مرة كل شهر في الربيع والصيف.",
    "benefits": "ينقي الهواء ويضفي جمالًا للمساحات الداخلية.",
   "warning": "غير سام للحيوانات الأليفة."
  },
  "9": {
   "name": "كلاثيا",
   "description": "نبات داخلي بأوراق مزخرفة تتحرك مع الضوء.",
   "light": "يفضل الضوء غير المباشر الساطع.",
   "temperature": "بين 18-25 ",
   "watering": "8",
    "soil": "تربة خفيفة جيدة التصريف.",
   "fertilization": "مرة شهريًا في الربيع والصيف.",
    "benefits": "يضفي جمالًا استوائيًا للمنازل ويعزز الرطوبة.",
    "warning": "غير سام للحيوانات الأليفة."
  },
"10": {
   "name": "نبات الحديد الزهر (أسبيديسترا إيلايتور) ",
   "description": "نبات داخلي دائم الخضرة بأوراق خضراء داكنة لامعة، يتميز بقدرته على التحمل في ظروف الإضاءة المنخفضة.",
   "light": "يتحمل الإضاءة المنخفضة ويفضل الضوء غير المباشر.",
   "temperature": "بين 7-29  ",
   "watering": "3",
   "soil": "تربة خفيفة جيدة التصريف.",
   "fertilization": "مرة كل شهر خلال فصلي الربيع والصيف.",
    "benefits": "ينقي الهواء ويضفي لمسة خضراء للمساحات الداخلية.",
    "warning": "غير سام للحيوانات الأليفة."
  },
  "11": {
    "name": "نبات المال الصيني (بيليا بيبروميويدس) ",
    "description": "نبات داخلي بأوراق مستديرة خضراء لامعة، يُعرف أيضًا باسم بيليا بيبيروميويدس.",
    "light": "يفضل الضوء الساطع غير المباشر.",
    "temperature": "بين 16-24 ",
    "watering": "6",
    "soil": "تربة جيدة التصريف.",
    "fertilization": "مرة كل شهر خلال فصلي الربيع والصيف.",
   "benefits": "يضفي لمسة عصرية للمساحات الداخلية.",
   "warning": "غير سام للحيوانات الأليفة."
  },
  "12": {
    "name": "أجلونيما",
    "description": "نبات داخلي دائم الخضرة بأوراق خضراء مع تدرجات فضية، يُعتبر من النباتات المنزلية الشهيرة.",
    "light": "يتحمل الإضاءة المنخفضة ويفضل الضوء غير المباشر.",
    "temperature": "بين 18-24 ",
    "watering": "5",
    "soil": "تربة خفيفة جيدة التصريف.",
    "fertilization": "مرة كل شهر خلال فصلي الربيع والصيف.",
    "benefits": "ينقي الهواء ويضفي لمسة خضراء للمساحات الداخلية.",
    "warning": "قد يكون سامًا للحيوانات الأليفة عند الابتلاع."
  },
  "13": {
    "name": "صبار عيد الميلاد (شلمبرجيرا بريدجيسي)",
    "description": "نبات عصاري مزهر بأزهار حمراء أو وردية تظهر في فصل الشتاء.",
    "light": "يفضل الضوء الساطع غير المباشر.",
    "temperature": "بين 15-24 ",
    "watering": "3",
   "soil": "تربة خفيفة جيدة التصريف.",
   "fertilization": "مرة كل شهر خلال فصلي الربيع والصيف.",
    "benefits": "يزهر في فصل الشتاء، مما يضفي جمالًا خلال هذه الفترة.",
    "warning": "غير سام للحيوانات الأليفة."
  },
  "14": {
    "name": "الأقحوان (كريسانثيوم) ",
    "description": "نبات مزهر بأزهار متعددة الألوان، يُستخدم كنبات زينة داخلي وخارجي.",
    "light": "يفضل الضوء الساطع المباشر.",
    "temperature": "بين 10-18 ",
    "watering": "8",
    "soil": "تربة خفيفة جيدة التصريف.",
    "fertilization": "مرة كل أسبوعين خلال فترة النمو.",
    "benefits": "يزين المساحات بأزهاره الجميلة والمتنوعة.",
    "warning": "قد يكون سامًا للحيوانات الأليفة عند الابتلاع."
  },
  "15": {
    "name": "كيتناتي",
    "description": "نبات داخلي بأوراق مزخرفة بألوان خضراء وبنفسجية.",
    "light": "يفضل الضوء غير المباشر الساطع.",
    "temperature": "بين 18-24 ",
    "watering": "8",
    "soil": "تربة خفيفة جيدة التصريف.",
   "fertilization": "مرة كل شهر خلال فصلي الربيع والصيف.",
   "benefits": "يضفي لمسة جمالية بأوراقه المزخرفة.",
    "warning": "غير سام للحيوانات الأليفة."
  },
  "16": {
   "name": "النرجس ( نارسيسوس)",
    "description": "نبات مزهر بأزهار صفراء أو بيضاء، يُزرع في الحدائق ويُستخدم كنبات داخلي مؤقت.",
    "light": "يفضل الضوء الساطع المباشر.",
   "temperature": "بين 10-15 ",
  "watering": "3",
  "soil": "تربة خفيفة جيدة التصريف.",
   "fertilization": "مرة كل أسبوعين خلال فترة النمو.",
   "benefits": "يزهر في أوائل الربيع، مما يضفي جمالًا للمساحات.",
"warning": "جميع أجزاء النبات سامة عند الابتلاع."
 },

 "17": {
   "name": "شجرة التنين (دراسينا)",
    "description": "نبات داخلي دائم الخضرة بأوراق طويلة وضيقة، يتنوع لونها بين الأخضر والأحمر.",
   "light": "يفضل الضوء غير المباشر المتوسط إلى الساطع.",
  "temperature": "بين 18-24 ",
  "watering": "2",
  "soil": "تربة خفيفة جيدة التصريف.",
  "fertilization": "مرة كل شهر خلال فصلي الربيع والصيف.",
  "benefits": "ينقي الهواء ويضفي لمسة استوائية للمساحات الداخلية.",
   "warning": "قد يكون سامًا للحيوانات الأليفة عند الابتلاع."
  },

  "18": {
    "name": "ديفنباخيا",
    "description": "نبات داخلي بأوراق كبيرة خضراء مع تدرجات بيضاء أو صفراء.",
    "light": "يفضل الضوء غير المباشر المتوسط.",
    "temperature": "بين 18-24",
    "watering": "2",
    "soil": "تربة خفيفة جيدة التصريف.",
   "fertilization": "مرة كل شهر خلال فصلي الربيع والصيف.",
   "benefits": "يضفي لمسة خضراء وجمالية للمساحات الداخلية.",
   "warning": "سام للحيوانات الأليفة والبشر عند الابتلاع."
  },
  "19": {
    "name": "أذن الفيل (ألوكاسيا) ",
    "description": "نبات داخلي بأوراق كبيرة سهمية الشكل، تتميز بعروق بارزة بلون مغاير للأخضر الداكن.",
   "light": "يفضل الضوء الساطع غير المباشر.",
    "temperature": "بين 18-21 ",
   "watering": "3",
    "soil": "تربة خفيفة جيدة التصريف.",
    "fertilization": "مرة شهريًا خلال فصلي الربيع والصيف.",
    "benefits": "يضفي لمسة استوائية وجمالية للمساحات الداخلية.",
    "warning": "سام للحيوانات الأليفة والبشر عند الابتلاع."
  },
  "20": {
    "name": "اللبلاب الإنجليزي ( هيدرا هيلكس) ",
    "description": "نبات متسلق دائم الخضرة بأوراق خضراء داكنة مفصصة، يُستخدم كنبات زينة داخلي وخارجي.",
    "light": "يفضل الضوء غير المباشر ويمكنه التحمل في الإضاءة المنخفضة.",
    "temperature": "بين 10-20 ",
    "watering": "2",
    "soil": "تربة خفيفة جيدة التصريف.",
   "fertilization": "مرة كل شهر خلال فصلي الربيع والصيف.",
  "benefits": "ينقي الهواء ويضفي لمسة خضراء للمساحات الداخلية.",
    "warning": "قد يكون سامًا للحيوانات الأليفة عند الابتلاع."
  },
  "21": {
   "name": "الياقوتية ( هياسينثوس أورينتاليس) ",
   "description": "نبات مزهر بأزهار عطرية متعددة الألوان، يُزرع في الحدائق ويُستخدم كنبات داخلي مؤقت.",
   "light": "يفضل الضوء الساطع غير المباشر.",
   "temperature": "بين 15-20 ",
   "watering": "2",
   "soil": "تربة خفيفة جيدة التصريف.",
   "fertilization": "مرة كل أسبوعين خلال فترة النمو.",
    "benefits": "يضفي رائحة عطرة وألوانًا زاهية للمساحات.",
    "warning": "قد يكون سامًا عند الابتلاع."
  },
  "22": {
 "name": "بيجونيا الصليب الحديدي (بيجونيا ميسونيانا) ",
 "description": "نبات داخلي بأوراق خضراء مزخرفة بعلامات بنية تشبه الصليب، وأزهار بيضاء أو وردية.",
 "light": "يفضل الضوء غير المباشر الساطع.",
  "temperature": "بين 18-24 ",
  "watering": "3",
   "soil": "تربة خفيفة جيدة التصريف.",
    "fertilization": "مرة كل شهر خلال فصلي الربيع والصيف.",
    "benefits": "يضفي لمسة جمالية بأوراقه المزخرفة.",
    "warning": "غير سام للحيوانات الأليفة."
  },
  "23": {
   "name": "نبات اليشم ( كراسولا أوفاتا)",
   "description": "نبات عصاري داخلي بأوراق سميكة خضراء لامعة، يُعتبر رمزًا للحظ والازدهار في بعض الثقافات.",
  "light": "يفضل الضوء الساطع المباشر.",
    "temperature": "بين 18-24 ",
   "watering": "1",
 "soil": "تربة خفيفة جيدة التصريف.",
  "fertilization": "مرة كل شهر خلال فصلي الربيع والصيف.",
   "benefits": "يضفي لمسة خضراء ويُعتقد أنه يجلب الحظ والازدهار.",
   "warning": "غير سام للحيوانات الأليفة."
  },
  "24": {
    "name": "كالانشو",
    "description": "نبات عصاري يتميز بأوراق سميكة وزهور زاهية تدوم لفترة طويلة",
    "light": "يفضل الضوء الساطع غير المباشر، ويمكنه تحمل بعض أشعة الشمس المباشرة",
    "temperature": "بين 15-25",
    "watering": "1",
    "soil": "تربة جيدة التصريف مثل خليط الصبار",
    "fertilization": "1",
    "benefits": "ينقي الهواء ويضفي لمسة جمالية بفضل أزهاره الملونة",
    "warning": "سام للحيوانات الأليفة عند الابتلاع"
  },
  "25": {
    "name": "الليليوم (زهرة الزنبق النهاري)",
    "description": "نبات مزهر بأزهار جميلة تتفتح خلال النهار وتأتي بألوان متعددة",
    "light": "يفضل التعرض لأشعة الشمس المباشرة إلى الجزئية",
    "temperature": "بين 18-30",
    "watering": "2",
    "soil": "تربة غنية جيدة التصريف",
    "fertilization": "مرتين شهريًا خلال موسم النمو",
    "benefits": "يضيف مظهرًا جذابًا للحدائق ويجذب الفراشات والنحل",
    "warning": "سام جدًا للقطط وقد يسبب مشاكل صحية عند الابتلاع"
  },
  "26": {
    "name": "زنبق الوادي",
    "description": "نبات معمر يتميز بأزهاره البيضاء الصغيرة ذات الرائحة العطرة",
    "light": "يفضل الظل الجزئي إلى الكامل",
    "temperature": "بين 15-24",
    "watering": "2",
    "soil": "تربة رطبة جيدة التصريف وغنية بالمغذيات",
    "fertilization": "مرة واحدة في أوائل الربيع",
    "benefits": "يستخدم في تنسيق الحدائق ويضفي رائحة زكية",
    "warning": "سام جدًا للإنسان والحيوانات عند الابتلاع"
  },
  "27": {
    "name": " شجرة المال (باتشيرا أكواتيكا)",
    "description": "نبات داخلي شائع يتميز بجذعه المضفر وأوراقه الخضراء اللامعة",
    "light": "يفضل الضوء الساطع غير المباشر ويمكنه تحمل الإضاءة المنخفضة",
    "temperature": "بين 18-30",
    "watering": "2",
    "soil": "تربة جيدة التصريف مثل خليط التربة الرملية",
    "fertilization": "مرة شهريًا خلال الربيع والصيف",
    "benefits": "يعتقد أنه يجلب الحظ والثروة، كما يساهم في تنقية الهواء",
    "warning": "غير سام للحيوانات الأليفة ولكنه قد يسبب اضطرابًا في المعدة عند الابتلاع"
  },
  "28": {
    "name": "مونستيرا ديليشوسا",
    "description": "نبات استوائي يتميز بأوراقه الكبيرة المفرغة التي تضفي لمسة جمالية رائعة",
    "light": "يفضل الضوء الساطع غير المباشر لكنه يتحمل الإضاءة المنخفضة",
    "temperature": "بين 18-30",
    "watering": "2",
    "soil": "تربة غنية جيدة التصريف مثل خليط البيتموس والبيرلايت",
    "fertilization": "مرة كل أسبوعين خلال موسم النمو",
    "benefits": "يعزز الديكور الداخلي وينقي الهواء من بعض السموم",
    "warning": "سام للحيوانات الأليفة عند الابتلاع"
  },
  "29": {
    "name": "الأوركيد",
    "description": "نبات زهري راقٍ يتميز بأزهاره الجميلة والمتنوعة في الألوان والأشكال",
    "light": "يفضل الضوء الساطع غير المباشر",
    "temperature": "بين 18-28",
    "watering": "1",
    "soil": "خليط خاص بالأوركيد مثل اللحاء والبيرلايت",
    "fertilization": "مرة كل أسبوعين بسماد مخفف خلال موسم النمو",
    "benefits": "يضفي لمسة فاخرة على الديكور الداخلي وينقي الهواء",
    "warning": "غير سام للإنسان والحيوانات الأليفة"
  },
  "30": {
    "name": " نخلة الصالون (تشاميدوريا إيليجانس)",
    "description": "نبات داخلي أنيق يتميز بأوراقه الريشية الخضراء وقدرته على التكيف مع الإضاءة المنخفضة",
    "light": "يفضل الضوء غير المباشر ولكنه يتحمل الإضاءة المنخفضة",
    "temperature": "بين 18-27",
    "watering": "2",
    "soil": "تربة جيدة التصريف مثل خليط التربة العضوية والبيرلايت",
    "fertilization": "مرة شهريًا خلال فصلي الربيع والصيف",
    "benefits": "ينقي الهواء من السموم ويضيف لمسة استوائية للمساحات الداخلية",
    "warning": "غير سام للإنسان والحيوانات الأليفة"
  },
  "31": {
    "name": "زنابق السلام",
    "description": "نبات داخلي جذاب بأوراق خضراء لامعة وزهور بيضاء أنيقة تشبه الشموع",
    "light": "يفضل الضوء غير المباشر المتوسط إلى الساطع، لكنه يتحمل الإضاءة المنخفضة",
    "temperature": "بين 18-30",
    "watering": "2",
    "soil": "تربة جيدة التصريف غنية بالمواد العضوية",
    "fertilization": "مرة كل 6 أسابيع خلال موسم النمو",
    "benefits": "ينقي الهواء من السموم مثل الفورمالديهايد والبنزين",
    "warning": "سام للحيوانات الأليفة عند الابتلاع"
  },
  "32": {
    "name": "بونسيتيا (يوبوربيا بولشيرريما)",
    "description": "نبات زينة شهير يتميز بأوراقه الحمراء الزاهية التي تشبه الأزهار",
    "light": "يفضل الضوء الساطع غير المباشر",
    "temperature": "بين 15-25",
    "watering": "2",
    "soil": "تربة جيدة التصريف مثل خليط البيتموس والبيرلايت",
    "fertilization": "مرة كل أسبوعين خلال موسم النمو",
    "benefits": "يضيف لمسة جمالية خاصة في المناسبات، خاصة في موسم الأعياد",
    "warning": "قد يسبب تهيجًا جلديًا واضطرابات في المعدة عند الابتلاع"
  },
  "33": {
    "name": "نبات البولكا دوت (هايبوستيس فيلوسيتاشيا) ",
    "description": "نبات زينة داخلي بأوراق مرقطة بألوان زاهية مثل الوردي والأبيض والأحمر",
    "light": "يفضل الضوء الساطع غير المباشر، لكنه يتحمل الإضاءة المتوسطة",
    "temperature": "بين 18-26",
    "watering": "3",
    "soil": "تربة جيدة التصريف غنية بالمواد العضوية",
    "fertilization": "مرة كل أسبوعين خلال فصلي الربيع والصيف",
    "benefits": "يضيف لمسة ديكورية جميلة بألوانه الزاهية",
    "warning": "غير سام، لكنه قد يسبب اضطرابات خفيفة في المعدة عند الحيوانات الأليفة"
  },
  "34": {
    "name": "نخلة ذيل الحصان (بوكارنيا ريكوفاتا) ",
    "description": "نبات عصاري مميز بقاعدة سميكة تشبه الجذع ويحمل أوراقًا طويلة ورفيعة تشبه ذيل الحصان",
    "light": "يفضل الضوء الساطع غير المباشر",
    "temperature": "بين 18-24",
    "watering": "2",
    "soil": "تربة خفيفة جيدة التصريف",
    "fertilization": "مرة شهريًا في الربيع والصيف",
    "benefits": "يعتبر من النباتات التي تنقي الهواء ويساعد في تحسين الجو الداخلي",
    "warning": "غير سام للحيوانات الأليفة"
  },
  "35": {
    "name": "بوتوس (إيفي أرم) ",
    "description": "نبات متسلق ذو أوراق قلبية الشكل، سهل العناية ويتميز بسرعة نموه في ظروف متنوعة",
    "light": "يفضل الضوء غير المباشر، لكنه يتحمل الضوء الخافت",
    "temperature": "بين 18-24",
    "watering": "4",
    "soil": "تربة خفيفة وجيدة التصريف",
    "fertilization": "1",
    "benefits": "يساعد في تنقية الهواء ويحسن من جودة البيئة الداخلية",
    "warning": "سام للحيوانات الأليفة"
  },
  "36": {
    "name": "مارانتا ليكونيورا",
    "description": "نبات داخلي ذو أوراق مزخرفة بألوان جميلة، يميزها حركة الأوراق ليلاً حيث ترفعها بشكل يشبه اليدين في الصلاة",
    "light": "يفضل الضوء غير المباشر الساطع",
    "temperature": "بين 18-24",
    "watering": "4",
    "soil": "تربة خفيفة جيدة التصريف",
    "fertilization": "مرة شهريًا في الربيع والصيف",
    "benefits": "يعتبر من النباتات التي تضفي جوًا هادئًا وجماليًا في المنازل",
    "warning": "غير سام للحيوانات الأليفة"
  },
  "37": {
    "name": "كالاثيا لانسيفوليا",
    "description": "نبات ذو أوراق طويلة ومخططة بشكل يشبه جلد الأفعى، يتميز بحركة أوراقه التي تنفتح وتغلق حسب الضوء",
    "light": "يفضل الضوء غير المباشر الساطع",
    "temperature": "بين 18-24",
    "watering": "4",
    "soil": "تربة خفيفة جيدة التصريف",
    "fertilization": "مرة شهريًا في الربيع والصيف",
    "benefits": "يساعد في تحسين نوعية الهواء في الأماكن المغلقة ويضيف لمسة جمالية للمنازل",
    "warning": "غير سام للحيوانات الأليفة"
  },
    "38": {
    "name": "نبات المطاط (فيكس إيلاستيك) ",
    "description": "نبات ذو أوراق لامعة وكبيرة، يشتهر بقدرته على النمو بسرعة في الظروف المناسبة",
    "light": "يفضل الضوء غير المباشر الساطع",
    "temperature": "بين 18-29",
    "watering": "4",
    "soil": "تربة غنية وجيدة التصريف",
    "fertilization": "مرة شهريًا في الربيع والصيف",
    "benefits": "يساعد في تحسين جودة الهواء داخل المنازل ويضفي لمسة جمالية رائعة",
    "warning": "سام للحيوانات الأليفة"
  },
  "39": {
    "name": "نخلة الساجو (سيكاس ريفولوتا) ",
    "description": "نبات استوائي يشبه النخيل، يتميز بأوراقه الخضراء اللامعة التي تنمو بشكل دائري حول الجذع",
    "light": "يفضل الضوء الساطع غير المباشر",
    "temperature": "بين 18-27",
    "watering": "4",
    "soil": "تربة خفيفة جيدة التصريف",
    "fertilization": "مرة شهريًا في الربيع والصيف",
    "benefits": "يضيف لمسة استوائية جميلة للمنازل والمكاتب",
    "warning": "سام للحيوانات الأليفة"
  },
  "40": {
    "name": "شيفليرا",
    "description": "نبات داخلي ذو أوراق لامعة وأسطوانية الشكل، ينمو بشكل كثيف ويمكن أن يصبح شجرة صغيرة إذا تم العناية به بشكل جيد",
    "light": "يفضل الضوء غير المباشر الساطع",
    "temperature": "بين 18-24",
    "watering": "4",
    "soil": "تربة خفيفة جيدة التصريف",
    "fertilization": "مرة شهريًا في الربيع والصيف",
    "benefits": "يساعد في تحسين جودة الهواء داخل المنزل ويضيف مظهرًا أخضر وجميلًا",
    "warning": "سام للحيوانات الأليفة"
  },
  "41": {
    "name": " نبات الأفعى (سانسيفيريا)",
    "description": "نبات عصاري ذو أوراق طويلة وشبيهة بالرمح، سهل العناية ويعتبر من أفضل النباتات التي تنقي الهواء",
    "light": "يتحمل الضوء المنخفض، لكنه يفضل الضوء غير المباشر الساطع",
    "temperature": "بين 15-29",
    "watering": "4",
    "soil": "تربة جيدة التصريف",
    "fertilization": "مرة شهريًا في الربيع والصيف",
    "benefits": "ينقي الهواء ويحسن من نوعية البيئة الداخلية",
    "warning": "سام للحيوانات الأليفة"
  },
  "42": {
    "name": "ترايديسكانتيا",
    "description": "نبات متسلق سريع النمو ذو أوراق ملونة بألوان متنوعة مثل البنفسجي والأخضر، سهل العناية ويضفي جمالاً داخليًا",
    "light": "يفضل الضوء غير المباشر الساطع",
    "temperature": "بين 18-24",
    "watering": "3",
    "soil": "تربة خفيفة جيدة التصريف",
    "fertilization": "مرة شهريًا في الربيع والصيف",
    "benefits": "يساعد في تنقية الهواء ويضيف لمسة جمالية للمنازل والمكاتب",
    "warning": "غير سام للحيوانات الأليفة"
  },
  "43": {
    "name": "توليب",
    "description": "نبات مزهر يتميز بأزهاره الجميلة والملونة التي تتفتح في فصل الربيع، ويعد من أشهر الزهور حول العالم",
    "light": "يفضل الضوء الساطع المباشر",
    "temperature": "بين 10-20",
    "watering": "4",
    "soil": "تربة جيدة التصريف وغنية بالعناصر الغذائية",
    "fertilization": "مرة شهريًا في موسم النمو",
    "benefits": "إضافة لمسة من الجمال في الحدائق والمنازل ويجذب النحل والفراشات",
    "warning": "غير سام للحيوانات الأليفة"
  },
  "44": {
    "name": "فخ الزنبق ",
    "description": "نبات مفترس يتميز بفخاخ تشبه الفكوك تلتقط الحشرات، ويعد من النباتات الغريبة التي تثير الفضول",
    "light": "يفضل الضوء الساطع غير المباشر",
    "temperature": "بين 20-30",
    "watering": "3",
    "soil": "تربة خفيفة وحامضية، مثل مزيج من الطحالب والرمل",
    "fertilization": "لا يحتاج للتسميد عادةً، حيث يحصل على غذائه من الحشرات",
    "benefits": "يساعد في تقليل الحشرات داخل الأماكن المغلقة",
    "warning": "غير سام للحيوانات الأليفة"
  },
  "45": {
    "name": "يوكا",
    "description": "نبات عصاري ذو أوراق طويلة وشوكية، يتميز بتحمله للظروف القاسية ويضفي مظهرًا استوائيًا في المنازل",
    "light": "يفضل الضوء الساطع المباشر",
    "temperature": "بين 18-24",
    "watering": "4",
    "soil": "تربة خفيفة وجيدة التصريف",
    "fertilization": "مرة شهريًا في الربيع والصيف",
    "benefits": "يساعد في تنقية الهواء ويضفي جمالًا استوائيًا على المساحات الداخلية",
    "warning": "غير سام للحيوانات الأليفة"
  },
  "46": {
    "name": "نبات ZZ (زاميوكولكاس زامييفوليا)",
    "description": "نبات مقاوم للجفاف يتميز بأوراق لامعة وسميكة، يعتبر من أسهل النباتات في العناية بها",
    "light": "يتحمل الضوء المنخفض، ولكنه يفضل الضوء غير المباشر الساطع",
    "temperature": "بين 18-24",
    "watering": "4",
    "soil": "تربة خفيفة جيدة التصريف",
    "fertilization": "مرة شهريًا في الربيع والصيف",
    "benefits": "يساعد في تنقية الهواء ويساهم في تحسين بيئة المنزل",
    "warning": "سام للحيوانات الأليفة"
  }
}
